polycloud/__init__.py
polycloud/bootstrap.py
polycloud/main.py
polycloud/controllers/__init__.py
polycloud/controllers/base.py
polycloud/controllers/srv.py
polycloud/core/__init__.py
polycloud/core/exc.py
polycloud/core/version.py
polycloud/ext/__init__.py
polycloud/plugins/__init__.py
polycloud/templates/__init__.py
polycloud/templates/command1.jinja2
polycloud/templates/generate/.DS_Store
polycloud/templates/generate/service/.generate.yml
polycloud/templates/generate/service/.gitignore
polycloud/templates/generate/service/CONTRIBUTING.md
polycloud/templates/generate/service/Dockerfile
polycloud/templates/generate/service/LICENSE
polycloud/templates/generate/service/README.md
polycloud/templates/generate/service/VERSION
polycloud/templates/generate/service/app.py
polycloud/templates/generate/service/docker-compose.yml
polycloud/templates/generate/service/requirements.txt
polycloud/templates/generate/service/sample.txt
polycloud/templates/generate/service/skaffold.yaml
polycloud/templates/generate/service/.circleci/config.yml
polycloud/templates/generate/service/.circleci/machine-setup.sh
polycloud/templates/generate/service/.github/CODEOWNERS
polycloud/templates/generate/service/.github/ISSUE_TEMPLATE.md
polycloud/templates/generate/service/.github/PULL_REQUEST_TEMPLATE.md
polycloud/templates/generate/service/api/auth.py
polycloud/templates/generate/service/api/identities.py
polycloud/templates/generate/service/devops/build-and-deploy.sh
polycloud/templates/generate/service/devops/config/authentication-policy.yaml
polycloud/templates/generate/service/devops/config/deployment.yaml
polycloud/templates/generate/service/devops/config/httpapispec.yaml
polycloud/templates/generate/service/devops/config/network.yaml
polycloud/templates/generate/service/swagger/swagger.yaml
polycloud/templates/generate/web/.editorconfig
polycloud/templates/generate/web/.eslintrc.js
polycloud/templates/generate/web/.generate.yml
polycloud/templates/generate/web/.gitattributes
polycloud-0.0.1.dev20181010211930.dist-info/LICENSE.md
polycloud-0.0.1.dev20181010211930.dist-info/METADATA
polycloud-0.0.1.dev20181010211930.dist-info/WHEEL
polycloud-0.0.1.dev20181010211930.dist-info/entry_points.txt
polycloud-0.0.1.dev20181010211930.dist-info/top_level.txt
polycloud-0.0.1.dev20181010211930.dist-info/RECORD
