Metadata-Version: 2.1
Name: polycloud
Version: 0.0.1.dev20181010211930
Summary: Manage your open polycloud platform.
Home-page: https://github.com/denseidel/platform/tree/master/cli
Author: Dennis Seidel
Author-email: denseidel@gmail.com
License: MIT
Platform: UNKNOWN
Requires-Dist: cement
Requires-Dist: jinja2
Requires-Dist: pyyaml
Requires-Dist: colorlog
